[
  {
    "brand": "TaylorMade",
    "model": "Stealth Plus",
    "year": 2022,
    "loft": 9.0,
    "launch": "Low-Mid",
    "forgiveness": "Moderate",
    "swing_speed": "Fast",
    "shot_shape_bias": "Neutral",
    "adjustability": true,
    "price": 579.99
  },
  {
    "brand": "Callaway",
    "model": "Paradym X",
    "year": 2023,
    "loft": 10.5,
    "launch": "High",
    "forgiveness": "Very High",
    "swing_speed": "Moderate",
    "shot_shape_bias": "Draw Bias",
    "adjustability": true,
    "price": 549.99
  },
  {
    "brand": "Ping",
    "model": "G425 Max",
    "year": 2021,
    "loft": 9.0,
    "launch": "Mid",
    "forgiveness": "High",
    "swing_speed": "Moderate-Fast",
    "shot_shape_bias": "Neutral",
    "adjustability": true,
    "price": 499.99
  },
  {
    "brand": "Titleist",
    "model": "TSR3",
    "year": 2022,
    "loft": 8.5,
    "launch": "Low",
    "forgiveness": "Moderate",
    "swing_speed": "Fast",
    "shot_shape_bias": "Neutral",
    "adjustability": true,
    "price": 599.99
  },
  {
    "brand": "Cobra",
    "model": "LTDx Max",
    "year": 2022,
    "loft": 10.5,
    "launch": "Mid-High",
    "forgiveness": "High",
    "swing_speed": "Moderate",
    "shot_shape_bias": "Draw Bias",
    "adjustability": true,
    "price": 449.99
  },
  {
    "brand": "Wilson",
    "model": "Launch Pad",
    "year": 2021,
    "loft": 12.0,
    "launch": "High",
    "forgiveness": "Very High",
    "swing_speed": "Slow-Moderate",
    "shot_shape_bias": "Draw Bias",
    "adjustability": false,
    "price": 299.99
  },
  {
    "brand": "Cleveland",
    "model": "Launcher XL",
    "year": 2022,
    "loft": 10.5,
    "launch": "High",
    "forgiveness": "Very High",
    "swing_speed": "Moderate",
    "shot_shape_bias": "Neutral",
    "adjustability": false,
    "price": 399.99
  },
  {
    "brand": "Tour Edge",
    "model": "Exotics E723",
    "year": 2023,
    "loft": 9.5,
    "launch": "Mid",
    "forgiveness": "High",
    "swing_speed": "Moderate-Fast",
    "shot_shape_bias": "Neutral",
    "adjustability": true,
    "price": 429.99
  },
  {
    "brand": "Mizuno",
    "model": "ST-Z 220",
    "year": 2022,
    "loft": 9.5,
    "launch": "Mid",
    "forgiveness": "Moderate",
    "swing_speed": "Fast",
    "shot_shape_bias": "Neutral",
    "adjustability": true,
    "price": 499.99
  },
  {
    "brand": "Srixon",
    "model": "ZX5 MKII",
    "year": 2022,
    "loft": 10.5,
    "launch": "Mid-High",
    "forgiveness": "High",
    "swing_speed": "Moderate",
    "shot_shape_bias": "Neutral",
    "adjustability": true,
    "price": 529.99
  },
  {
    "brand": "PXG",
    "model": "0311 XF Gen 5",
    "year": 2023,
    "loft": 9.0,
    "launch": "Mid",
    "forgiveness": "Very High",
    "swing_speed": "Fast",
    "shot_shape_bias": "Neutral",
    "adjustability": true,
    "price": 699.99
  },
  {
    "brand": "Honma",
    "model": "TR20",
    "year": 2021,
    "loft": 9.5,
    "launch": "Low-Mid",
    "forgiveness": "Moderate",
    "swing_speed": "Fast",
    "shot_shape_bias": "Fade Bias",
    "adjustability": true,
    "price": 649.99
  },
  {
    "brand": "Callaway",
    "model": "Rogue ST Max",
    "year": 2022,
    "loft": 10.5,
    "launch": "Mid-High",
    "forgiveness": "High",
    "swing_speed": "Moderate",
    "shot_shape_bias": "Neutral",
    "adjustability": true,
    "price": 529.99
  },
  {
    "brand": "TaylorMade",
    "model": "SIM2 Max",
    "year": 2021,
    "loft": 12.0,
    "launch": "High",
    "forgiveness": "Very High",
    "swing_speed": "Slow-Moderate",
    "shot_shape_bias": "Draw Bias",
    "adjustability": true,
    "price": 479.99
  },
  {
    "brand": "Cobra",
    "model": "AeroJet Max",
    "year": 2023,
    "loft": 10.5,
    "launch": "Mid-High",
    "forgiveness": "High",
    "swing_speed": "Moderate",
    "shot_shape_bias": "Draw Bias",
    "adjustability": true,
    "price": 499.99
  },
  {
    "brand": "Ping",
    "model": "G410 Plus",
    "year": 2020,
    "loft": 9.0,
    "launch": "Mid",
    "forgiveness": "High",
    "swing_speed": "Moderate-Fast",
    "shot_shape_bias": "Neutral",
    "adjustability": true,
    "price": 429.99
  },
  {
    "brand": "Titleist",
    "model": "TSi2",
    "year": 2021,
    "loft": 10.0,
    "launch": "Mid",
    "forgiveness": "High",
    "swing_speed": "Moderate-Fast",
    "shot_shape_bias": "Neutral",
    "adjustability": true,
    "price": 549.99
  },
  {
    "brand": "Wilson",
    "model": "Staff Model",
    "year": 2022,
    "loft": 9.0,
    "launch": "Low",
    "forgiveness": "Moderate",
    "swing_speed": "Fast",
    "shot_shape_bias": "Neutral",
    "adjustability": false,
    "price": 399.99
  },
  {
    "brand": "Cleveland",
    "model": "Launcher HB Turbo",
    "year": 2020,
    "loft": 10.5,
    "launch": "High",
    "forgiveness": "Very High",
    "swing_speed": "Slow",
    "shot_shape_bias": "Neutral",
    "adjustability": false,
    "price": 329.99
  },
  {
    "brand": "Tour Edge",
    "model": "Hot Launch C522",
    "year": 2022,
    "loft": 10.5,
    "launch": "Mid-High",
    "forgiveness": "High",
    "swing_speed": "Moderate",
    "shot_shape_bias": "Neutral",
    "adjustability": false,
    "price": 299.99
  },
  {
    "brand": "Srixon",
    "model": "ZX7",
    "year": 2021,
    "loft": 9.5,
    "launch": "Low-Mid",
    "forgiveness": "Moderate",
    "swing_speed": "Fast",
    "shot_shape_bias": "Neutral",
    "adjustability": true,
    "price": 479.99
  },
  {
    "brand": "Callaway",
    "model": "Big Bertha B21",
    "year": 2021,
    "loft": 12.5,
    "launch": "High",
    "forgiveness": "Very High",
    "swing_speed": "Slow",
    "shot_shape_bias": "Draw Bias",
    "adjustability": true,
    "price": 499.99
  },
  {
    "brand": "TaylorMade",
    "model": "R15",
    "year": 2019,
    "loft": 10.5,
    "launch": "Mid",
    "forgiveness": "Moderate",
    "swing_speed": "Moderate",
    "shot_shape_bias": "Neutral",
    "adjustability": true,
    "price": 349.99
  },
  {
    "brand": "Ping",
    "model": "G400",
    "year": 2017,
    "loft": 9.0,
    "launch": "Mid-Low",
    "forgiveness": "High",
    "swing_speed": "Fast",
    "shot_shape_bias": "Neutral",
    "adjustability": true,
    "price": 399.99
  },
  {
    "brand": "Cobra",
    "model": "King F9",
    "year": 2019,
    "loft": 9.5,
    "launch": "Mid",
    "forgiveness": "High",
    "swing_speed": "Moderate-Fast",
    "shot_shape_bias": "Neutral",
    "adjustability": true,
    "price": 429.99
  },
  {
    "brand": "Titleist",
    "model": "TS2",
    "year": 2018,
    "loft": 10.5,
    "launch": "High",
    "forgiveness": "High",
    "swing_speed": "Moderate",
    "shot_shape_bias": "Neutral",
    "adjustability": true,
    "price": 499.99
  },
  {
    "brand": "Mizuno",
    "model": "ST190",
    "year": 2019,
    "loft": 9.5,
    "launch": "Mid",
    "forgiveness": "Moderate",
    "swing_speed": "Fast",
    "shot_shape_bias": "Neutral",
    "adjustability": false,
    "price": 449.99
  },
  {
    "brand": "Wilson",
    "model": "D7",
    "year": 2020,
    "loft": 10.5,
    "launch": "Mid-High",
    "forgiveness": "High",
    "swing_speed": "Moderate",
    "shot_shape_bias": "Neutral",
    "adjustability": false,
    "price": 349.99
  },
  {
    "brand": "Cleveland",
    "model": "Launcher Turbo",
    "year": 2019,
    "loft": 9.5,
    "launch": "Mid",
    "forgiveness": "High",
    "swing_speed": "Moderate-Fast",
    "shot_shape_bias": "Neutral",
    "adjustability": false,
    "price": 379.99
  },
  {
    "brand": "Tour Edge",
    "model": "Exotics EXS",
    "year": 2019,
    "loft": 10.5,
    "launch": "Mid-High",
    "forgiveness": "High",
    "swing_speed": "Moderate",
    "shot_shape_bias": "Neutral",
    "adjustability": true,
    "price": 399.99
  },
  {
    "brand": "PXG",
    "model": "0811 X",
    "year": 2020,
    "loft": 9.0,
    "launch": "Low-Mid",
    "forgiveness": "Moderate",
    "swing_speed": "Fast",
    "shot_shape_bias": "Neutral",
    "adjustability": true,
    "price": 575.00
  },
  {
    "brand": "Honma",
    "model": "TW747",
    "year": 2019,
    "loft": 10.5,
    "launch": "Mid",
    "forgiveness": "Moderate",
    "swing_speed": "Moderate",
    "shot_shape_bias": "Neutral",
    "adjustability": true,
    "price": 549.99
  },
  {
    "brand": "Srixon",
    "model": "Z785",
    "year": 2018,
    "loft": 9.5,
    "launch": "Low-Mid",
    "forgiveness": "Moderate",
    "swing_speed": "Fast",
    "shot_shape_bias": "Fade Bias",
    "adjustability": true,
    "price": 429.99
  },
  {
    "brand": "Callaway",
    "model": "Epic Flash",
    "year": 2019,
    "loft": 10.5,
    "launch": "Mid-High",
    "forgiveness": "High",
    "swing_speed": "Moderate",
    "shot_shape_bias": "Neutral",
    "adjustability": true,
    "price": 529.99
  },
  {
    "brand": "TaylorMade",
    "model": "M5",
    "year": 2019,
    "loft": 9.0,
    "launch": "Low",
    "forgiveness": "Moderate",
    "swing_speed": "Fast",
    "shot_shape_bias": "Neutral",
    "adjustability": true,
    "price": 499.99
  },
  {
    "brand": "Ping",
    "model": "G400 Max",
    "year": 2018,
    "loft": 10.5,
    "launch": "Mid-High",
    "forgiveness": "Very High",
    "swing_speed": "Moderate",
    "shot_shape_bias": "Neutral",
    "adjustability": true,
    "price": 435.00
  },
  {
    "brand": "Cobra",
    "model": "F8+",
    "year": 2018,
    "loft": 9.5,
    "launch": "Mid",
    "forgiveness": "High",
    "swing_speed": "Moderate-Fast",
    "shot_shape_bias": "Neutral",
    "adjustability": true,
    "price": 399.99
  },
  {
    "brand": "Titleist",
    "model": "917 D2",
    "year": 2017,
    "loft": 10.5,
    "launch": "Mid",
    "forgiveness": "High",
    "swing_speed": "Moderate",
    "shot_shape_bias": "Neutral",
    "adjustability": true,
    "price": 479.99
  },
  {
    "brand": "Mizuno",
    "model": "JPX 919",
    "year": 2018,
    "loft": 9.5,
    "launch": "Mid-Low",
    "forgiveness": "Moderate",
    "swing_speed": "Fast",
    "shot_shape_bias": "Neutral",
    "adjustability": false,
    "price": 399.99
  },
  {
    "brand": "Wilson",
    "model": "Cortex",
    "year": 2020,
    "loft": 10.5,
    "launch": "Mid-High",
    "forgiveness": "High",
    "swing_speed": "Moderate",
    "shot_shape_bias": "Draw Bias",
    "adjustability": false,
    "price": 329.99
  },
  {
    "brand": "Cleveland",
    "model": "Launcher CBX",
    "year": 2019,
    "loft": 9.5,
    "launch": "Mid",
    "forgiveness": "High",
    "swing_speed": "Moderate-Fast",
    "shot_shape_bias": "Neutral",
    "adjustability": false,
    "price": 359.99
  },
  {
    "brand": "Tour Edge",
    "model": "Exotic EXS 220",
    "year": 2020,
    "loft": 10.5,
    "launch": "Mid-High",
    "forgiveness": "High",
    "swing_speed": "Moderate",
    "shot_shape_bias": "Neutral",
    "adjustability": true,
    "price": 419.99
  },
  {
    "brand": "PXG",
    "model": "0811 Gen2",
    "year": 2019,
    "loft": 9.0,
    "launch": "Low-Mid",
    "forgiveness": "Moderate",
    "swing_speed": "Fast",
    "shot_shape_bias": "Neutral",
    "adjustability": true,
    "price": 625.00
  },
  {
    "brand": "Honma",
    "model": "TW737",
    "year": 2018,
    "loft": 10.5,
    "launch": "Mid",
    "forgiveness": "Moderate",
    "swing_speed": "Moderate",
    "shot_shape_bias": "Neutral",
    "adjustability": true,
    "price": 499.99
  },
  {
    "brand": "Srixon",
    "model": "Z945",
    "year": 2017,
    "loft": 9.5,
    "launch": "Low",
    "forgiveness": "Moderate",
    "swing_speed": "Fast",
    "shot_shape_bias": "Neutral",
    "adjustability": true,
    "price": 399.99
  },
  {
    "brand": "Callaway",
    "model": "Mavrik",
    "year": 2020,
    "loft": 10.5,
    "launch": "Mid-High",
    "forgiveness": "High",
    "swing_speed": "Moderate",
    "shot_shape_bias": "Neutral",
    "adjustability": true,
    "price": 499.99
  },
  {
    "brand": "TaylorMade",
    "model": "M6",
    "year": 2019,
    "loft": 9.0,
    "launch": "Mid",
    "forgiveness": "High",
    "swing_speed": "Moderate-Fast",
    "shot_shape_bias": "Neutral",
    "adjustability": true,
    "price": 479.99
  }
]
